atquant/__init__.py
atquant/account/__init__.py
atquant/account/account_checker.pyc
atquant/api/__init__.py
atquant/api/init_set.pyc
atquant/at_algorithm/__init__.py
atquant/at_algorithm/core_algorithm.pyc
atquant/data/__init__.py
atquant/data/basic_data.pyc
atquant/data/const_data.pyc
atquant/data/global_variable.pyc
atquant/examples/test_twolines.py
atquant/indicators/__init__.py
atquant/run_mode/__init__.py
atquant/run_mode/run_mode_common.pyc
atquant/run_mode/trader_run_back_test.pyc
atquant/run_mode/trader_run_real_trade.pyc
atquant/run_mode/trader_run_replay.pyc
atquant/socket_ctrl/__init__.py
atquant/socket_ctrl/base_socket.pyc
atquant/socket_ctrl/tool_box_command.pyc
atquant/strategy/__init__.py
atquant/trade/__init__.py
atquant/trade/back_test_trade.pyc
atquant/utils/__init__.py
atquant/utils/arg_checker.pyc
atquant/utils/datetime_func.pyc
atquant/utils/internal_exception.pyc
atquant/utils/internal_util.pyc
atquant/utils/lang_tr.pyc
atquant/utils/logger.pyc
atquant/utils/logging_dict.json
atquant/utils/user_class.pyc
atquant-2.3.846.dist-info/DESCRIPTION.rst
atquant-2.3.846.dist-info/METADATA
atquant-2.3.846.dist-info/RECORD
atquant-2.3.846.dist-info/WHEEL
atquant-2.3.846.dist-info/metadata.json
atquant-2.3.846.dist-info/top_level.txt
